LICENSE
README.md
README.rst
setup.py
polylib/__init__.py
polylib/bernoulli.py
polylib/polynomial.py
polylib/polynomials.py
polylib/py.typed
polylib/utils.py
polylib.egg-info/PKG-INFO
polylib.egg-info/SOURCES.txt
polylib.egg-info/dependency_links.txt
polylib.egg-info/entry_points.txt
polylib.egg-info/not-zip-safe
polylib.egg-info/requires.txt
polylib.egg-info/top_level.txt
svgs/016f77d11a1eae7a49443e3c252c19c9.svg
svgs/02df0effbe2654713e6c577b3617238b.svg
svgs/03b68175a4091303003398ce95493a7e.svg
svgs/03b6b5f46a1a8db86910fa766534e026.svg
svgs/0423aef2a8675301835de97021681953.svg
svgs/0528690f9c580f0213178d39c1cb262f.svg
svgs/06c08830cb3dd840f4e6802aa980d26d.svg
svgs/07639cc30e3014dbc769f3c8170ac244.svg
svgs/0899ab0ce9b5609bfa7dad876092ab1a.svg
svgs/0912d30774bbcaea29aeabf3fb370c2b.svg
svgs/0b31a35771b3af5ede73661d6ee5fb1b.svg
svgs/0b5b44ebd94846018794d7cef12465dc.svg
svgs/0d22f407954da5086c12b23dab9a95d1.svg
svgs/0d3450deab45553a7209ac1763ed6bd1.svg
svgs/0d5d6e639f683b34cdfedc73232a0bbf.svg
svgs/0ddd6bcbd634aa4e4fca0d417007980d.svg
svgs/0e4bf00376fc90803a2bceaaf165b1d3.svg
svgs/0e51a2dede42189d77627c4d742822c3.svg
svgs/0f452ec0bcf578fa387e4857f80f03f4.svg
svgs/100caa207d95c5e7ba7d084fdab1423e.svg
svgs/11bf421c7c0e7f47f014283bb60d9128.svg
svgs/134d1b0038e1a0d69eaf61a9c8f4f0a6.svg
svgs/14f910bc51b9d1d442f82027720000e1.svg
svgs/15cc700a4eb36c0d28e1bf24c4c71cd1.svg
svgs/16d9f56f984735eb405cdf7376bdb3f2.svg
svgs/176f15256170856ba1785008876eb5eb.svg
svgs/179b9a85f34653eab0cc78fce58dc665.svg
svgs/1862585f60c285b14a6775143add6dc2.svg
svgs/190083ef7a1625fbc75f243cffb9c96d.svg
svgs/1b1ed27418bdfd527e9ed9ebe217cd84.svg
svgs/1b4c29076ce02dbd2b2f66909c74f5d7.svg
svgs/1bbc927b28c3d87639c0a2b6fea7bae9.svg
svgs/1da9fcafafb5c088ab6ddc5e21359621.svg
svgs/1e1f23cedaa9debed279fcb962dfe67f.svg
svgs/1e58ba22c02aa26896cb29061e779d11.svg
svgs/1f16c9c0c00e8c4b99d34ed0628b1985.svg
svgs/202b298f34df7fbda3f152db9acdc869.svg
svgs/2103f85b8b1477f430fc407cad462224.svg
svgs/213bfe60dd1eff3fa603b6961c5a7f98.svg
svgs/21e9fd1c6fa0fcc7289cf659d74e1bb2.svg
svgs/21edb67019b99109f0af63a13878f539.svg
svgs/2463781e8bfdf91dd19ea58a46e18ede.svg
svgs/2478063ebe0ce1d945693b61fef683da.svg
